{
  "sync_time": "2026-01-16T15:01:29.498779",
  "results": [
    {
      "scraper": "KAHRAMAA",
      "started_at": "2026-01-16T15:01:20.064894",
      "success": true,
      "stations_processed": 0,
      "error": null,
      "stdout": "=== KAHRAMAA Charging Station Scraper ===\n\nFetching stations page...\n  \u2717 Error fetching stations page: HTTPSConnectionPool(host='www.hugedomains.com', port=443): Max retries exceeded with url: /domain_profile.cfm?d=kahramaa.com (Caused by NewConnectionError('<urllib3.connection.HTTPSConnection object at 0x75e22931b410>: Failed to establish a new connection: [Errno 111] Connection refused'))\nFailed to fetch page. Exiting.\n",
      "stderr": "",
      "completed_at": "2026-01-16T15:01:21.454885"
    },
    {
      "scraper": "WOQOD",
      "started_at": "2026-01-16T15:01:21.454993",
      "success": true,
      "stations_processed": 0,
      "error": null,
      "stdout": "=== WOQOD Charging Station Scraper ===\n\nFetching station data...\nFound 5 stations\n\n[1/5] WOQOD - Abu Hamour\n  Address: Abu Hamour, Doha, Qatar\n  Chargers: 4 x 50kW\n  Connectors: Type 2, CCS\n  \u2717 Supabase update failed: 400\n  \u2717 Failed to update station\n  \u2713 Charger availability updated\n\n[2/5] WOQOD - Al Khor\n  Address: Al Khor, Qatar\n  Chargers: 2 x 50kW\n  Connectors: Type 2, CCS\n  \u2717 Supabase update failed: 400\n  \u2717 Failed to update station\n  \u26a0 Could not update charger availability\n\n[3/5] WOQOD - Al Wakra\n  Address: Al Wakra, Qatar\n  Chargers: 2 x 50kW\n  Connectors: Type 2, CCS\n  \u2717 Supabase update failed: 400\n  \u2717 Failed to update station\n  \u26a0 Could not update charger availability\n\n[4/5] WOQOD - Dukhan\n  Address: Dukhan, Qatar\n  Chargers: 2 x 22kW\n  Connectors: Type 2\n  \u2717 Supabase update failed: 400\n  \u2717 Failed to update station\n  \u26a0 Could not update charger availability\n\n[5/5] WOQOD - Industrial Area\n  Address: Industrial Area, Doha, Qatar\n  Chargers: 3 x 50kW\n  Connectors: Type 2, CCS\n  \u2717 Supabase update failed: 400\n  \u2717 Failed to update station\n  \u26a0 Could not update charger availability\n\n=== Complete ===\nProcessed 5 WOQOD stations\n",
      "stderr": "",
      "completed_at": "2026-01-16T15:01:29.498607"
    }
  ],
  "summary": {
    "total_scrapers": 2,
    "successful": 2,
    "failed": 0,
    "total_stations": 0
  }
}